README.rst
setup.py
fastqmetrics/__init__.py
fastqmetrics/fastqmetrics.py
fastqmetrics/version.py
fastqmetrics.egg-info/PKG-INFO
fastqmetrics.egg-info/SOURCES.txt
fastqmetrics.egg-info/dependency_links.txt
fastqmetrics.egg-info/entry_points.txt
fastqmetrics.egg-info/requires.txt
fastqmetrics.egg-info/top_level.txt