Metadata-Version: 1.1
Name: fastqmetrics
Version: 0.1.0
Summary: Het hoeft voor 
Home-page: https://github.com/wdecoster/fastqmetrics
Author: Wouter De Coster
Author-email: decosterwouter@gmail.com
License: MIT
Keywords: nanopore sequencing processing
Platform: UNKNOWN
Classifier: Development Status :: 4 - Beta
Classifier: Intended Audience :: Science/Research
Classifier: Topic :: Scientific/Engineering :: Bio-Informatics
Classifier: License :: OSI Approved :: MIT License
Classifier: Programming Language :: Python :: 3
Classifier: Programming Language :: Python :: 3.3
Classifier: Programming Language :: Python :: 3.4
Classifier: Programming Language :: Python :: 3.5
